dexa_protocol/.DS_Store
dexa_protocol/__init__.py
dexa_protocol/definition.py
dexa_protocol/v1_0/__init__.py
dexa_protocol/v1_0/handlers/__init__.py
dexa_protocol/v1_0/handlers/accept_dda_handler.py
dexa_protocol/v1_0/handlers/dda_negotiation_receipt_handler.py
dexa_protocol/v1_0/handlers/deactivate_dda_handler.py
dexa_protocol/v1_0/handlers/delete_dda_handler.py
dexa_protocol/v1_0/handlers/list_marketplace_dda_handler.py
dexa_protocol/v1_0/handlers/offer_dda_handler.py
dexa_protocol/v1_0/handlers/publish_dda_handler.py
dexa_protocol/v1_0/handlers/pulldata_notification_handler.py
dexa_protocol/v1_0/handlers/pulldata_request_handler.py
dexa_protocol/v1_0/handlers/pulldata_response_handler.py
dexa_protocol/v1_0/handlers/request_dda_handler.py
dexa_protocol/v1_0/message_types.py
dexa_protocol/v1_0/messages/__init__.py
dexa_protocol/v1_0/messages/deactivate_dda.py
dexa_protocol/v1_0/messages/marketplace/__init__.py
dexa_protocol/v1_0/messages/marketplace/delete_dda.py
dexa_protocol/v1_0/messages/marketplace/list_marketplace_dda.py
dexa_protocol/v1_0/messages/marketplace/list_marketplace_dda_response.py
dexa_protocol/v1_0/messages/marketplace/publish_dda.py
dexa_protocol/v1_0/messages/negotiation/__init__.py
dexa_protocol/v1_0/messages/negotiation/accept_dda.py
dexa_protocol/v1_0/messages/negotiation/dda_negotiation_receipt.py
dexa_protocol/v1_0/messages/negotiation/offer_dda.py
dexa_protocol/v1_0/messages/negotiation/request_dda.py
dexa_protocol/v1_0/messages/pulldata_notification_message.py
dexa_protocol/v1_0/messages/pulldata_request_message.py
dexa_protocol/v1_0/messages/pulldata_response_message.py
dexa_protocol/v1_0/models/__init__.py
dexa_protocol/v1_0/models/accept_dda_model.py
dexa_protocol/v1_0/models/dda_negotiation_receipt_model.py
dexa_protocol/v1_0/models/deactivate_dda_model.py
dexa_protocol/v1_0/models/delete_dda_model.py
dexa_protocol/v1_0/models/list_marketplace_dda_response_model.py
dexa_protocol/v1_0/models/offer_dda_model.py
dexa_protocol-0.1.11.dist-info/LICENSE
dexa_protocol-0.1.11.dist-info/WHEEL
dexa_protocol-0.1.11.dist-info/METADATA
dexa_protocol-0.1.11.dist-info/RECORD
