Metadata-Version: 2.1
Name: dexa-protocol
Version: 0.1.11
Summary: Hosts Data Disclosure Agreement protocols
Home-page: https://github.com/decentralised-dataexchange/dexa-protocol
License: License :: OSI Approved :: Apache Software License
Keywords: acapy,aries,dataexchange,ssi
Author: George J Padayatti
Author-email: george.padayatti@igrant.io
Requires-Python: >=3.8,<4.0
Classifier: License :: Other/Proprietary License
Classifier: Programming Language :: Python :: 3
Classifier: Programming Language :: Python :: 3.10
Classifier: Programming Language :: Python :: 3.8
Classifier: Programming Language :: Python :: 3.9
Classifier: Topic :: Software Development :: Build Tools
Classifier: Topic :: Software Development :: Libraries :: Python Modules
Requires-Dist: acapy-patched (==0.5.6-dev1)
Requires-Dist: dexa-sdk (==0.1.14)
Project-URL: Repository, https://github.com/decentralised-dataexchange/dexa-protocol
